idem_gcp/conf.py
idem_gcp/version.py
idem_gcp/acct/gcp/service_account.py
idem_gcp/acct/gcp/contracts/init.py
idem_gcp/autogen/init.py
idem_gcp/autogen/gcp/schema_parser.py
idem_gcp/exec/gcp/cloudkms/crypto_key.py
idem_gcp/exec/gcp/cloudkms/crypto_key_version.py
idem_gcp/exec/gcp/cloudkms/import_job.py
idem_gcp/exec/gcp/cloudkms/key_ring.py
idem_gcp/exec/gcp/cloudkms/location.py
idem_gcp/exec/gcp/compute/accelerator_type.py
idem_gcp/exec/gcp/compute/backend_service.py
idem_gcp/exec/gcp/compute/disk.py
idem_gcp/exec/gcp/compute/disk_type.py
idem_gcp/exec/gcp/compute/firewall.py
idem_gcp/exec/gcp/compute/forwarding_rule.py
idem_gcp/exec/gcp/compute/health_check.py
idem_gcp/exec/gcp/compute/image.py
idem_gcp/exec/gcp/compute/instance.py
idem_gcp/exec/gcp/compute/instance_group.py
idem_gcp/exec/gcp/compute/machine_image.py
idem_gcp/exec/gcp/compute/machine_type.py
idem_gcp/exec/gcp/compute/network.py
idem_gcp/exec/gcp/compute/node_template.py
idem_gcp/exec/gcp/compute/reservation.py
idem_gcp/exec/gcp/compute/resource_policy.py
idem_gcp/exec/gcp/compute/snapshot.py
idem_gcp/exec/gcp/compute/subnetwork.py
idem_gcp/exec/gcp/compute/target_pool.py
idem_gcp/exec/gcp/compute/zone.py
idem_gcp/exec/gcp/contracts/init.py
idem_gcp/exec/gcp/iam/service_account.py
idem_gcp/exec/gcp/iam/service_account_key.py
idem_gcp/exec/gcp/storage/bucket.py
idem_gcp/exec/gcp_api/init.py
idem_gcp/helpers/exc.py
idem_gcp/helpers/log.py
idem_gcp/helpers/returns.py
idem_gcp/metadata/gcp/cloudkms/projects/locations/init.py
idem_gcp/metadata/gcp/cloudkms/projects/locations/key_rings/init.py
idem_gcp/metadata/gcp/cloudkms/projects/locations/key_rings/crypto_keys/crypto_key_versions.py
idem_gcp/metadata/gcp/cloudkms/projects/locations/key_rings/crypto_keys/init.py
idem_gcp/metadata/gcp/cloudkms/projects/locations/key_rings/import_jobs/init.py
idem_gcp/metadata/gcp/compute/accelerator_type.py
idem_gcp/metadata/gcp/compute/backend_service.py
idem_gcp/metadata/gcp/compute/disk.py
idem_gcp-2.2.4.dist-info/LICENSE
idem_gcp-2.2.4.dist-info/METADATA
idem_gcp-2.2.4.dist-info/WHEEL
idem_gcp-2.2.4.dist-info/top_level.txt
idem_gcp-2.2.4.dist-info/RECORD
