Metadata-Version: 2.1
Name: idem-gcp
Version: 2.2.4
Summary: GCP Cloud Provider for Idem
Home-page: https://gitlab.com/vmware/idem/idem-gcp
Author: VMware, Inc.
Author-email: idemproject@vmware.com
License: Apache Software License 2.0
Project-URL: Code, https://gitlab.com/vmware/idem/idem-gcp
Project-URL: Issue tracker, https://gitlab.com/vmware/idem/idem-gcp/-/issues
Classifier: Environment :: Console
Classifier: Intended Audience :: Developers
Classifier: Intended Audience :: Information Technology
Classifier: Intended Audience :: System Administrators
Classifier: Operating System :: OS Independent
Classifier: Programming Language :: Python
Classifier: Programming Language :: Python :: 3.8
Classifier: Programming Language :: Python :: 3.9
Classifier: Programming Language :: Python :: 3.10
Classifier: Programming Language :: Python :: 3.11
Classifier: Development Status :: 5 - Production/Stable
Classifier: License :: OSI Approved :: Apache Software License
Requires-Python: >=3.8
License-File: LICENSE
Requires-Dist: google-api-python-client >=2.88.0
Requires-Dist: idem !=23.1.3,>=21.1.0
Requires-Dist: aiohttp >=3.8.4
Requires-Dist: idem-aiohttp >=3.0.0
Requires-Dist: pop >=26.0.3
Requires-Dist: deepdiff >=5.8.1
Requires-Dist: importlib-resources >=5.9.0
Requires-Dist: PyYaml >=6.0.1
Provides-Extra: autogen
Requires-Dist: pop-create-idem >=3.0.0 ; extra == 'autogen'
Requires-Dist: typing-extensions >=4.4.0 ; extra == 'autogen'
Provides-Extra: full
Requires-Dist: pop-create-idem >=3.0.0 ; extra == 'full'
Requires-Dist: typing-extensions >=4.4.0 ; extra == 'full'
